raapimtnmomo/__init__.py
raapimtnmomo/config.py
raapimtnmomo/create_api_user.py
raapimtnmomo/exceptions.py
raapimtnmomo/mtn_momo.py
raapimtnmomo/mtn_momo_collection.py
raapimtnmomo/mtn_momo_disbursement.py
raapimtnmomo/mtn_momo_remittance.py
raapimtnmomo/requestss.py
raapimtnmomo/sandbox_user_provisioning.py
raapimtnmomo/token_manager.py
raapimtnmomo/utilities.py
raapimtnmomo-0.1.2.dist-info/LICENSE
raapimtnmomo-0.1.2.dist-info/METADATA
raapimtnmomo-0.1.2.dist-info/WHEEL
raapimtnmomo-0.1.2.dist-info/entry_points.txt
raapimtnmomo-0.1.2.dist-info/top_level.txt
raapimtnmomo-0.1.2.dist-info/RECORD
