Metadata-Version: 2.1
Name: raapimtnmomo
Version: 0.1.2
Summary: A package to interact with MTN MoMo API in Sandbox Mode
Home-page: https://github.com/roazagba/apimtnmomo-python
Author: Roméo AZAGBA
Author-email: roazagba@gmail.com
Classifier: Programming Language :: Python :: 3
Classifier: License :: OSI Approved :: MIT License
Classifier: Operating System :: OS Independent
Requires-Python: >=3.10
License-File: LICENSE
